qt_json_setting/__init__.py
qt_json_setting-0.7.dist-info/LICENSE
qt_json_setting-0.7.dist-info/METADATA
qt_json_setting-0.7.dist-info/WHEEL
qt_json_setting-0.7.dist-info/top_level.txt
qt_json_setting-0.7.dist-info/RECORD
