Metadata-Version: 2.1
Name: qt-json-setting
Version: 0.7
Summary: 根据json schema生成设置界面
Home-page: https://github.com/ovo-Tim/pyqt-json-settingt
Author: ovo-tim
Author-email: ovo-tim@qq.com
Classifier: Programming Language :: Python :: 3
Classifier: License :: OSI Approved :: GNU General Public License v3 or later (GPLv3+)
Classifier: Operating System :: OS Independent
License-File: LICENSE
Requires-Dist: Pyside6
Requires-Dist: jsonschema
Requires-Dist: ujson
